CHANGES.rst
MANIFEST.in
README.rst
setup.cfg
setup.py
redshift_sqlalchemy/__init__.py
sqlalchemy_redshift/__init__.py
sqlalchemy_redshift/commands.py
sqlalchemy_redshift/compat.py
sqlalchemy_redshift/dialect.py
sqlalchemy_redshift/redshift-ssl-ca-cert.pem
sqlalchemy_redshift_psycopg2cffi.egg-info/PKG-INFO
sqlalchemy_redshift_psycopg2cffi.egg-info/SOURCES.txt
sqlalchemy_redshift_psycopg2cffi.egg-info/dependency_links.txt
sqlalchemy_redshift_psycopg2cffi.egg-info/entry_points.txt
sqlalchemy_redshift_psycopg2cffi.egg-info/requires.txt
sqlalchemy_redshift_psycopg2cffi.egg-info/top_level.txt