Metadata-Version: 1.1
Name: sqlalchemy-redshift-psycopg2cffi
Version: 0.5.1.dev1
Summary: Amazon Redshift Dialect for sqlalchemy
Home-page: https://github.com/LyuGGang/sqlalchemy-redshift
Author: LyuGGang
Author-email: me@lyuwonkyung.com
License: MIT
Platform: UNKNOWN
Classifier: Development Status :: 4 - Beta
Classifier: Environment :: Console
Classifier: Intended Audience :: Developers
Classifier: License :: OSI Approved :: MIT License
Classifier: Operating System :: OS Independent
Classifier: Programming Language :: Python
Classifier: Programming Language :: Python :: 2
Classifier: Programming Language :: Python :: 2.6
Classifier: Programming Language :: Python :: 2.7
Classifier: Programming Language :: Python :: 3
Classifier: Programming Language :: Python :: 3.3
Classifier: Programming Language :: Python :: 3.4
Classifier: Programming Language :: Python :: 3.5
